{"timestamp": 1762164026.7506163, "stats": {"total_classifications": 1, "total_errors": 0, "error_rate": 0.0, "average_confidence": 1.0, "intent_distribution": {"GREETING": 1}, "confidence_distribution": {"high": 1}, "response_times": {"min": 2309.4167709350586, "max": 2309.4167709350586, "avg": 2309.4167709350586, "total": 2309.4167709350586}, "last_updated": 1762164021.7447114}, "type": "hourly_summary"}
{"timestamp": 1762164041.7827246, "stats": {"total_classifications": 2, "total_errors": 0, "error_rate": 0.0, "average_confidence": 1.0, "intent_distribution": {"GREETING": 2}, "confidence_distribution": {"high": 2}, "response_times": {"min": 2309.4167709350586, "max": 20855.86428642273, "avg": 11582.640528678894, "total": 23165.281057357788}, "last_updated": 1762164040.2855034}, "type": "hourly_summary"}
{"timestamp": 1762164088.4991698, "stats": {"total_classifications": 1, "total_errors": 0, "error_rate": 0.0, "average_confidence": 1.0, "intent_distribution": {"GREETING": 1}, "confidence_distribution": {"high": 1}, "response_times": {"min": 1767.066478729248, "max": 1767.066478729248, "avg": 1767.066478729248, "total": 1767.066478729248}, "last_updated": 1762164083.4854188}, "type": "hourly_summary"}
{"timestamp": 1762164098.5175278, "stats": {"total_classifications": 2, "total_errors": 0, "error_rate": 0.0, "average_confidence": 1.0, "intent_distribution": {"GREETING": 2}, "confidence_distribution": {"high": 2}, "response_times": {"min": 1767.066478729248, "max": 16100.123405456543, "avg": 8933.594942092896, "total": 17867.18988418579}, "last_updated": 1762164097.8283572}, "type": "hourly_summary"}
{"timestamp": 1762164103.5343542, "stats": {"total_classifications": 3, "total_errors": 0, "error_rate": 0.0, "average_confidence": 1.0, "intent_distribution": {"GREETING": 2, "GENERAL_CHAT": 1}, "confidence_distribution": {"high": 3}, "response_times": {"min": 1767.066478729248, "max": 16100.123405456543, "avg": 6586.438099543254, "total": 19759.31429862976}, "last_updated": 1762164100.734685}, "type": "hourly_summary"}
{"timestamp": 1762164118.568023, "stats": {"total_classifications": 5, "total_errors": 0, "error_rate": 0.0, "average_confidence": 1.0, "intent_distribution": {"GREETING": 2, "GENERAL_CHAT": 3}, "confidence_distribution": {"high": 5}, "response_times": {"min": 1767.066478729248, "max": 16100.123405456543, "avg": 7594.900369644165, "total": 37974.501848220825}, "last_updated": 1762164118.0616908}, "type": "hourly_summary"}
{"timestamp": 1762164128.5844598, "stats": {"total_classifications": 6, "total_errors": 0, "error_rate": 0.0, "average_confidence": 1.0, "intent_distribution": {"GREETING": 2, "GENERAL_CHAT": 4}, "confidence_distribution": {"high": 6}, "response_times": {"min": 1767.066478729248, "max": 16100.123405456543, "avg": 7926.114757855733, "total": 47556.6885471344}, "last_updated": 1762164124.889372}, "type": "hourly_summary"}
